chrome_proxy-1.0.2.dist-info/METADATA
chrome_proxy-1.0.2.dist-info/WHEEL
chrome_proxy-1.0.2.dist-info/entry_points.txt
chrome_proxy/__init__.py
chrome_proxy/chrome_manager.py
chrome_proxy/proxy_app.py
chrome_proxy-1.0.2.dist-info/RECORD
