Metadata-Version: 2.1
Name: chrome-proxy
Version: 1.0.2
Summary: chrome remote debug proxy
Author-Email: funcdefmain <741132517@qq.com>
License: MIT
Requires-Python: >=3.10
